promptdrifter/__init__.py
promptdrifter/adapter_manager.py
promptdrifter/cache.py
promptdrifter/cli.py
promptdrifter/drift_types.py
promptdrifter/http_client_manager.py
promptdrifter/runner.py
promptdrifter/yaml_loader.py
promptdrifter/adapters/__init__.py
promptdrifter/adapters/base.py
promptdrifter/adapters/claude.py
promptdrifter/adapters/deepseek.py
promptdrifter/adapters/gemini.py
promptdrifter/adapters/grok.py
promptdrifter/adapters/llama.py
promptdrifter/adapters/mistral.py
promptdrifter/adapters/ollama.py
promptdrifter/adapters/openai.py
promptdrifter/adapters/qwen.py
promptdrifter/adapters/models/__init__.py
promptdrifter/adapters/models/claude_models.py
promptdrifter/adapters/models/deepseek_models.py
promptdrifter/adapters/models/gemini_models.py
promptdrifter/adapters/models/grok_models.py
promptdrifter/adapters/models/llama_models.py
promptdrifter/adapters/models/mistral_models.py
promptdrifter/adapters/models/ollama_models.py
promptdrifter/adapters/models/openai_models.py
promptdrifter/adapters/models/qwen_models.py
promptdrifter/config/__init__.py
promptdrifter/config/adapter_settings.py
promptdrifter/metrics/__init__.py
promptdrifter/metrics/base.py
promptdrifter/metrics/core.py
promptdrifter/metrics/token_overlap.py
promptdrifter/models/__init__.py
promptdrifter/models/config.py
promptdrifter/schema/README.md
promptdrifter/schema/__init__.py
promptdrifter/schema/constants.py
promptdrifter/schema/migration.py
promptdrifter/schema/update_symlinks.py
promptdrifter/schema/validator.py
promptdrifter/schema/latest/sample.yaml
promptdrifter/schema/latest/schema.json
promptdrifter-0.0.2.dist-info/METADATA
promptdrifter-0.0.2.dist-info/WHEEL
promptdrifter-0.0.2.dist-info/entry_points.txt
promptdrifter-0.0.2.dist-info/licenses/LICENSE
promptdrifter-0.0.2.dist-info/RECORD
